{
  "users": {
    "omes": {
      "items": [
        {
          "id": 1765080738930,
          "type": "pawn",
          "name": "ทองตัวเอง",
          "amount": 1000,
          "paidMonth": 0,
          "isPaused": false,
          "pawnMode": "baht",
          "fixed_int": 12.5,
          "date": "2025-12-02",
          "expireDate": "2026-04-02"
        },
        {
          "id": 1765080820667,
          "type": "pawn",
          "name": "ทองของแม่ยืมจำ",
          "amount": 22000,
          "paidMonth": 0,
          "isPaused": false,
          "pawnMode": "baht",
          "fixed_int": 275,
          "date": "2025-10-19",
          "expireDate": "2026-02-19"
        },
        {
          "id": 1765081226653,
          "type": "expense",
          "name": "ให้ลูก",
          "amount": 1000,
          "paidMonth": 0,
          "isPaused": false,
          "isPaid": false
        },
        {
          "id": 1765081247700,
          "type": "expense",
          "name": "ค่าเรียนพิเศษลูก",
          "amount": 500,
          "paidMonth": 0,
          "isPaused": false,
          "isPaid": false
        },
        {
          "id": 1765081293651,
          "type": "expense",
          "name": "ค่าเน็ตมือถือแม่",
          "amount": 426.93,
          "paidMonth": 0,
          "isPaused": false,
          "isPaid": false
        }
      ],
      "history": [],
      "planMode": false,
      "planMonths": 6,
      "minLiving": 0
    }
  }
}